CBioNAMER
nner
