Metadata-Version: 2.1
Name: CBioNAMER
Version: 1.0
Summary: Nested Named Entity Recognition for Chinese Biomedical Text
Home-page: https://github.com/cb1cyf/CBioNAMER/
Author: Yufeng Cheng
Author-email: 2101210556@pku.edu.cn
License: UNKNOWN
Platform: UNKNOWN
Classifier: Programming Language :: Python :: 3
Classifier: License :: OSI Approved :: MIT License
Classifier: Operating System :: OS Independent
Requires-Python: >=3
